AUTHORS.rst
CONTRIBUTING.rst
HISTORY.rst
LICENSE
MANIFEST.in
README.rst
setup.py
easyengine/__init__.py
easyengine/base.py
easyengine/exceptions.py
easyengine/util.py
easyengine/version.py
easyengine/resources/__init__.py
easyengine/resources/base.py
easyengine/resources/clean.py
easyengine/resources/install.py
easyengine/resources/secure.py
easyengine/resources/site.py
easyengine/resources/stack.py
python_easyengine.egg-info/PKG-INFO
python_easyengine.egg-info/SOURCES.txt
python_easyengine.egg-info/dependency_links.txt
python_easyengine.egg-info/requires.txt
python_easyengine.egg-info/top_level.txt