Metadata-Version: 1.1
Name: python-easyengine
Version: 0.5.0
Summary: EasyEngine Python Module
Home-page: https://github.com/cubope/python-easyengine
Author: Cubo
Author-email: somos@cubo.pe
License: Apache License 2.0
Keywords: python,easyengine,management
Platform: UNKNOWN
Classifier: Development Status :: 4 - Beta
Classifier: Intended Audience :: Developers
Classifier: License :: OSI Approved :: Apache Software License
Classifier: Programming Language :: Python :: 2.6
Classifier: Programming Language :: Python :: 2.7
Classifier: Programming Language :: Python :: 3.2
Classifier: Programming Language :: Python :: 3.3
Classifier: Programming Language :: Python :: 3.4
Classifier: Programming Language :: Python :: 3.5
Classifier: Topic :: Software Development :: Libraries
Classifier: Topic :: Utilities
Classifier: Environment :: Web Environment
